juliohmtools/__init__.py
juliohmtools/k8scontroller.py
juliohmtools/vcswatch.py
juliohmtools/vcswatchclient.py
juliohmtools-0.2.0.dist-info/LICENSE
juliohmtools-0.2.0.dist-info/METADATA
juliohmtools-0.2.0.dist-info/WHEEL
juliohmtools-0.2.0.dist-info/top_level.txt
juliohmtools-0.2.0.dist-info/RECORD
